ml_lime_xai/__init__.py
ml_lime_xai/text_reader.py
ml_lime_xai/data/my_code.py
ml_lime_xai-0.1.dist-info/METADATA
ml_lime_xai-0.1.dist-info/WHEEL
ml_lime_xai-0.1.dist-info/top_level.txt
ml_lime_xai-0.1.dist-info/RECORD
