Metadata-Version: 2.1
Name: ml-lime-xai
Version: 0.1
Summary: Code for XAI using Lime (Breast Cancer Dataset)
Home-page: https://github.com/savioratharv/prac_testing
Author: davinci003
Author-email: freegpt00@gmail.com
